samp_query/__init__.py
samp_query/py.typed
samp_query/rcon.py
samp_query-0.6.0.dist-info/METADATA
samp_query-0.6.0.dist-info/WHEEL
samp_query-0.6.0.dist-info/entry_points.txt
samp_query-0.6.0.dist-info/licenses/LICENSE
samp_query-0.6.0.dist-info/RECORD
